espeakng/__init__.py
espeakng-1.0.2.dist-info/LICENSE.txt
espeakng-1.0.2.dist-info/METADATA
espeakng-1.0.2.dist-info/WHEEL
espeakng-1.0.2.dist-info/top_level.txt
espeakng-1.0.2.dist-info/RECORD
