Metadata-Version: 2.1
Name: espeakng
Version: 1.0.2
Summary: An eSpeak NG TTS binding for Python3
Home-page: https://sayak-brm.github.io/espeakng-python/
Author: Sayak B
Author-email: me@sayakb.com
License: UNKNOWN
Keywords: tts,espeak,speakng,speech
Platform: UNKNOWN
Classifier: Development Status :: 4 - Beta
Classifier: Intended Audience :: Developers
Classifier: Programming Language :: Python :: 3 :: Only
Classifier: License :: OSI Approved :: GNU General Public License v3 (GPLv3)
Classifier: Programming Language :: Python :: 3.5
Classifier: Programming Language :: Python :: 3.6
Classifier: Programming Language :: Python :: 3.7
Classifier: Programming Language :: Python :: 3.8
Classifier: Programming Language :: Python :: 3.9
Requires-Python: >=3.5
